simplests/__init__.py
simplests/model_args.py
simplests/util.py
simplests/algo/__init__.py
simplests/algo/cls.py
simplests/algo/labse.py
simplests/algo/sbert.py
simplests/algo/sif.py
simplests/algo/use.py
simplests/algo/wmd.py
simplests/algo/word_avg.py
simplests-2.3.0.dist-info/LICENSE
simplests-2.3.0.dist-info/METADATA
simplests-2.3.0.dist-info/WHEEL
simplests-2.3.0.dist-info/top_level.txt
simplests-2.3.0.dist-info/RECORD
