Metadata-Version: 2.1
Name: simplests
Version: 2.3.0
Summary: Unsupervised models for Semantic Textual Similarity
Home-page: https://github.com/TharinduDR/Simple-Sentence-Similarity
Author: Tharindu Ranasinghe
Author-email: rhtdranasinghe@gmail.com
Classifier: Intended Audience :: Science/Research
Classifier: License :: OSI Approved :: Apache Software License
Classifier: Programming Language :: Python :: 3
Classifier: Topic :: Scientific/Engineering :: Artificial Intelligence
Requires-Python: >=3.6
License-File: LICENSE
Requires-Dist: pandas
Requires-Dist: numpy
Requires-Dist: flair
Requires-Dist: tqdm
Requires-Dist: pyemd
Requires-Dist: stop-words
Requires-Dist: tensorflow-text
Requires-Dist: tensorflow-hub
Requires-Dist: sentence-transformers
